{
  "schemaVersion": 1,
  "testType": "cross-repo-health-probe",
  "storyId": "S1-13",
  "timestamp": "2026-06-10T04:19:22.352Z",
  "environment": "staging",
  "overall": "FAIL",
  "services": [
    {
      "name": "sovereign",
      "repo": "gtcx-platforms",
      "url": "https://sovereign-staging.gtcx.trade/api/health",
      "status": "000",
      "error": "fetch failed",
      "body": null,
      "latencyMs": 546,
      "required": true
    },
    {
      "name": "agx-api",
      "repo": "gtcx-platforms",
      "url": "https://api.staging.gtcx.trade/api/health",
      "status": 200,
      "error": null,
      "body": {
        "status": "up",
        "timestamp": "2026-06-10T04:19:22.451Z",
        "database": {
          "status": "up",
          "details": {
            "type": "postgres"
          }
        },
        "protocol-adapters": {
          "status": "up",
          "details": {
            "expectedVersions": {
              "tradepass": "1.0.0",
              "geotag": "1.0.0",
              "gci": "1.0.0",
              "vaultmark": "1.0.0",
              "panx": "1.0.0"
            }
          }
        },
        "audit-trail": {
          "status": "up",
          "details": {
            "lastAppend": "2026-06-10T04:19:22.451Z",
            "chainVerified": true
          }
        }
      },
      "latencyMs": 3095,
      "required": true
    },
    {
      "name": "intelligence",
      "repo": "gtcx-intelligence",
      "url": "https://intelligence-staging.gtcx.trade/health",
      "status": "000",
      "error": "fetch failed",
      "body": null,
      "latencyMs": 507,
      "required": true
    },
    {
      "name": "compliance-gateway",
      "repo": "gtcx-infrastructure",
      "url": "https://compliance-gateway-staging.gtcx.trade/health",
      "status": "000",
      "error": "fetch failed",
      "body": null,
      "latencyMs": 506,
      "required": false
    }
  ],
  "summary": {
    "total": 4,
    "healthy": 1,
    "unhealthy": 3,
    "requiredUnhealthy": 2
  }
}
